spinsolveproc/__init__.py
spinsolveproc/cli.py
spinsolveproc/ngread_modified.py
spinsolveproc/plot.py
spinsolveproc/process.py
spinsolveproc/py.typed
spinsolveproc/save.py
spinsolveproc/spinsolveproc.py
spinsolveproc/utils.py
spinsolveproc-0.2.2.dist-info/LICENSE.rst
spinsolveproc-0.2.2.dist-info/METADATA
spinsolveproc-0.2.2.dist-info/WHEEL
spinsolveproc-0.2.2.dist-info/entry_points.txt
spinsolveproc-0.2.2.dist-info/RECORD
