Metadata-Version: 2.3
Name: spinsolveproc
Version: 0.2.2
Summary: Python library to process Spinsolve NMR experiments.
Keywords: spinsolveproc
Author: Raquel Serial
Author-email: raquelserial@gmail.com>
Requires-Python: <3.13,>=3.10
Classifier: Development Status :: 2 - Pre-Alpha
Classifier: Intended Audience :: Developers
Classifier: License :: OSI Approved :: GNU General Public License v3 (GPLv3)
Classifier: Natural Language :: English
Classifier: Programming Language :: Python :: 3
Classifier: Programming Language :: Python :: 3.10
Classifier: Programming Language :: Python :: 3.11
Classifier: Programming Language :: Python :: 3.12
Requires-Dist: flintpy-nmr (>=0.1.1,<1.0.0)
Requires-Dist: h5py (>=3.12.1,<4.0.0)
Requires-Dist: nmrglue (>=0.11,<1.0)
Requires-Dist: numpy (>=2.1.3,<3.0.0)
Requires-Dist: pandas (>=2.2.3,<3.0.0)
Requires-Dist: plotly (>=5.24.1,<6.0.0)
Requires-Dist: typer[all] (>=0.12.5,<1.0.0)
Project-URL: Bug Tracker, https://github.com/rserial/spinsolveproc/issues
Project-URL: documentation, https://spinsolveproc.readthedocs.io
Project-URL: homepage, https://github.com/rserial/spinsolveproc
Project-URL: repository, https://github.com/rserial/spinsolveproc
